file_navigator/__init__.py
file_navigator/abc_loader.py
file_navigator/loaders.py
file_navigator/matching.py
file_navigator/pathfinder.py
file_navigator-0.1.5.dist-info/LICENSE
file_navigator-0.1.5.dist-info/METADATA
file_navigator-0.1.5.dist-info/WHEEL
file_navigator-0.1.5.dist-info/top_level.txt
file_navigator-0.1.5.dist-info/RECORD
