Metadata-Version: 2.1
Name: file-navigator
Version: 0.1.5
Summary: Flexible directory scanner, file path manager, and customizable file loader—all in one
Author: Qomp4ss
Author-email: Qomp4ss <imaggine@gmail.com>
Maintainer: Qomp4ss
Maintainer-email: Qomp4ss <imaggine@gmail.com>
License: MIT License
Project-URL: Homepage, https://github.com/Qomp4ss/file-navigator
Keywords: file,flexible,manager,directory,scanner,path
Classifier: Programming Language :: Python :: 3
Classifier: License :: OSI Approved :: MIT License
Classifier: Operating System :: Microsoft :: Windows :: Windows 10
Requires-Python: >=3.6
License-File: LICENSE
Requires-Dist: pandas >=0.22
